aiobalaboba/__init__.py
aiobalaboba/_balaboba.py
aiobalaboba/_http.py
aiobalaboba/_text_type.py
aiobalaboba/py.typed
aiobalaboba-3.0.3.dist-info/LICENSE
aiobalaboba-3.0.3.dist-info/METADATA
aiobalaboba-3.0.3.dist-info/WHEEL
aiobalaboba-3.0.3.dist-info/RECORD
