Metadata-Version: 2.1
Name: aiobalaboba
Version: 3.0.3
Summary: Asynchronous wrapper for Yandex Balaboba
Home-page: https://github.com/monosans/aiobalaboba
License: MIT
Keywords: yalm
Author: monosans
Author-email: hsyqixco@protonmail.com
Requires-Python: >=3.7,<4.0
Classifier: Environment :: Web Environment
Classifier: Framework :: AsyncIO
Classifier: Intended Audience :: Developers
Classifier: Intended Audience :: Information Technology
Classifier: License :: OSI Approved :: MIT License
Classifier: Natural Language :: English
Classifier: Natural Language :: Russian
Classifier: Operating System :: OS Independent
Classifier: Programming Language :: Python
Classifier: Programming Language :: Python :: 3
Classifier: Programming Language :: Python :: 3.7
Classifier: Programming Language :: Python :: 3.8
Classifier: Programming Language :: Python :: 3.9
Classifier: Programming Language :: Python :: 3.10
Classifier: Programming Language :: Python :: 3.11
Classifier: Programming Language :: Python :: 3 :: Only
Classifier: Topic :: Internet
Classifier: Topic :: Internet :: WWW/HTTP
Classifier: Topic :: Software Development
Classifier: Topic :: Software Development :: Libraries
Classifier: Topic :: Software Development :: Libraries :: Python Modules
Classifier: Typing :: Typed
Requires-Dist: aiohttp (>=3.8,<4.0)
Requires-Dist: typing-extensions (>=3.7.4.3,<5) ; python_version < "3.8"
Project-URL: Documentation, https://aiobalaboba.readthedocs.io/
Project-URL: Repository, https://github.com/monosans/aiobalaboba
